_pybinding.cp38-win_amd64.pyd
pybinding/__about__.py
pybinding/__init__.py
pybinding/chebyshev.py
pybinding/constants.py
pybinding/greens.py
pybinding/lattice.py
pybinding/leads.py
pybinding/model.py
pybinding/modifier.py
pybinding/parallel.py
pybinding/pltutils.py
pybinding/results.py
pybinding/shape.py
pybinding/solver.py
pybinding/system.py
pybinding/repository/__init__.py
pybinding/repository/examples.py
pybinding/repository/group6_tmd.py
pybinding/repository/phosphorene.py
pybinding/repository/graphene/__init__.py
pybinding/repository/graphene/constants.py
pybinding/repository/graphene/lattice.py
pybinding/repository/graphene/modifiers.py
pybinding/repository/graphene/shape.py
pybinding/repository/graphene/utils.py
pybinding/support/__init__.py
pybinding/support/alias.py
pybinding/support/collections.py
pybinding/support/deprecated.py
pybinding/support/fuzzy_set.py
pybinding/support/inspect.py
pybinding/support/kwant.py
pybinding/support/pickle.py
pybinding/support/structure.py
pybinding/tests/__init__.py
pybinding/tests/conftest.py
pybinding/tests/local.cfg
pybinding/tests/test_kpm.py
pybinding/tests/test_kwant.py
pybinding/tests/test_lattice.py
pybinding/tests/test_leads.py
pybinding/tests/test_model.py
pybinding/tests/test_modifiers.py
pybinding/tests/test_parallel.py
pybinding/tests/test_pickle.py
pybinding/tests/test_results.py
pybinding/tests/test_shape.py
pybinding/tests/test_solver.py
pybinding/tests/test_system.py
pybinding/tests/test_wrapper.py
pybinding/tests/baseline_data/kpm/conductivity[graphene-const_potential].pbz
pybinding/tests/baseline_data/kpm/conductivity[graphene-magnetic_field].pbz
pybinding/tests/baseline_data/kpm/dos[graphene-const_potential].pbz
pybinding/tests/baseline_data/kpm/dos[graphene-magnetic_field].pbz
pybinding/tests/baseline_data/kpm/ldos[graphene-const_potential].pbz
pybinding/tests/baseline_data/kpm/ldos[graphene-magnetic_field].pbz
pybinding/tests/baseline_data/kpm/ldos[graphene-pristine-oversized].pbz
pybinding-0.9.5.dist-info/METADATA
pybinding-0.9.5.dist-info/WHEEL
pybinding-0.9.5.dist-info/license.md
pybinding-0.9.5.dist-info/top_level.txt
pybinding-0.9.5.dist-info/RECORD
