Metadata-Version: 2.1
Name: pybinding
Version: 0.9.5
Summary: Package for tight-binding calculations
Home-page: https://github.com/dean0x7d/pybinding
Author: Dean Moldovan
Author-email: dean0x7d@gmail.com
License: BSD
Keywords: pybinding tight-binding solid-state physics cmt
Platform: Unix
Platform: Windows
Classifier: Development Status :: 4 - Beta
Classifier: Intended Audience :: Science/Research
Classifier: Topic :: Scientific/Engineering :: Physics
Classifier: License :: OSI Approved :: BSD License
Classifier: Programming Language :: C++
Classifier: Programming Language :: Python :: 3 :: Only
Classifier: Programming Language :: Python :: 3.6
Classifier: Programming Language :: Python :: 3.7
Classifier: Programming Language :: Python :: 3.8
Classifier: Programming Language :: Python :: Implementation :: CPython
Requires-Dist: numpy (>=1.12)
Requires-Dist: scipy (>=0.19)
Requires-Dist: matplotlib (>=2.0)
Requires-Dist: pytest (>=5.0)
